PyMultiHelper/Conversion.py
PyMultiHelper/Dates.py
PyMultiHelper/Generation.py
PyMultiHelper/Lists.py
PyMultiHelper/Logging.py
PyMultiHelper/Network.py
PyMultiHelper/Represent.py
PyMultiHelper/Strings.py
PyMultiHelper/Validation.py
PyMultiHelper/Web.py
PyMultiHelper/__init__.py
pymultihelper-1.1.20.dist-info/licenses/LICENSE
pymultihelper-1.1.20.dist-info/METADATA
pymultihelper-1.1.20.dist-info/WHEEL
pymultihelper-1.1.20.dist-info/top_level.txt
pymultihelper-1.1.20.dist-info/RECORD
