Metadata-Version: 2.4
Name: PyMultiHelper
Version: 1.1.20
Summary: Several common helpers for Python coding
Home-page: https://github.com/anderbytes/PyMultiHelper
Author: Anderson
Author-email: anderbytes@gmail.com
License-File: LICENSE
Requires-Dist: requests>=2.32.3
Requires-Dist: pytz>=2024.2
Requires-Dist: pandas>=2.3.2
Requires-Dist: speedtest-cli>=2.1.3
Requires-Dist: beautifulsoup4>=4.12.3
Dynamic: author
Dynamic: author-email
Dynamic: description
Dynamic: description-content-type
Dynamic: home-page
Dynamic: license-file
Dynamic: requires-dist
Dynamic: summary
